eventum_cli/__init__.py
eventum_cli/__main__.py
eventum_cli/cli_compose.py
eventum_cli/cli_main.py
eventum_cli/config_finalizer.py
eventum_cli/logging_config.py
eventum_cli/py.typed
eventum_cli/resolver.py
eventum_cli/validation_prettier.py
eventum_cli-1.1.0.dist-info/LICENSE
eventum_cli-1.1.0.dist-info/METADATA
eventum_cli-1.1.0.dist-info/WHEEL
eventum_cli-1.1.0.dist-info/entry_points.txt
eventum_cli-1.1.0.dist-info/RECORD
